svision/__init__.py
svision/aircv/__init__.py
svision/aircv/aircv.py
svision/aircv/cal_confidence.py
svision/aircv/cv.py
svision/aircv/error.py
svision/aircv/keypoint_base.py
svision/aircv/keypoint_matching.py
svision/aircv/keypoint_matching_contrib.py
svision/aircv/multiscale_template_matching.py
svision/aircv/resolution.py
svision/aircv/settings.py
svision/aircv/sift.py
svision/aircv/template.py
svision/aircv/template_matching.py
svision/aircv/transform.py
svision/aircv/utils.py
svision/options/__init__.py
svision/orc/__init__.py
svision/utils/__init__.py
svision/utils/log_utils.py
solidvision-1.0.0.dist-info/METADATA
solidvision-1.0.0.dist-info/WHEEL
solidvision-1.0.0.dist-info/licenses/LICENSE
solidvision-1.0.0.dist-info/RECORD
