Metadata-Version: 2.4
Name: solidvision
Version: 1.0.0
Summary: 图像识别与文字识别模块 - 轻量级独立 OCR/CV 模块
Project-URL: Homepage, https://github.com/SolidQA/supervision
Project-URL: Repository, https://github.com/SolidQA/supervision
Project-URL: Bug Tracker, https://github.com/SolidQA/supervision/issues
Author-email: caishilong <1103837067@qq.com>
License: MIT
License-File: LICENSE
Keywords: computer-vision,image-recognition,ocr,opencv,paddleocr,template-matching,text-recognition
Classifier: Development Status :: 5 - Production/Stable
Classifier: Intended Audience :: Developers
Classifier: License :: OSI Approved :: MIT License
Classifier: Programming Language :: Python :: 3
Classifier: Programming Language :: Python :: 3.12
Classifier: Topic :: Scientific/Engineering :: Image Recognition
Classifier: Topic :: Software Development :: Libraries :: Python Modules
Requires-Python: <3.13,>=3.12
Requires-Dist: colorlog>=6.10.1
Requires-Dist: logzero>=1.7.0
Requires-Dist: matplotlib>=3.10.8
Requires-Dist: numpy>=2.4.1
Requires-Dist: opencv-contrib-python>=4.13.0.90
Requires-Dist: packaging>=26.0
Requires-Dist: paddleocr>=2.10.0
Requires-Dist: paddlepaddle==2.6.2
Requires-Dist: pillow>=12.1.0
Requires-Dist: requests>=2.32.5
Requires-Dist: setuptools>=80.10.2
